odoo/addons/pms_ocr_regula/README.rst
odoo/addons/pms_ocr_regula/__init__.py
odoo/addons/pms_ocr_regula/__manifest__.py
odoo/addons/pms_ocr_regula/data/pms_ocr_regula_data.xml
odoo/addons/pms_ocr_regula/models/__init__.py
odoo/addons/pms_ocr_regula/models/pms_property.py
odoo/addons/pms_ocr_regula/readme/CONTRIBUTORS.rst
odoo/addons/pms_ocr_regula/readme/DESCRIPTION.rst
odoo/addons/pms_ocr_regula/readme/USAGE.rst
odoo/addons/pms_ocr_regula/static/description/icon.png
odoo/addons/pms_ocr_regula/static/description/index.html
odoo14_addon_pms_ocr_regula-14.0.1.0.2.dev3.dist-info/METADATA
odoo14_addon_pms_ocr_regula-14.0.1.0.2.dev3.dist-info/WHEEL
odoo14_addon_pms_ocr_regula-14.0.1.0.2.dev3.dist-info/top_level.txt
odoo14_addon_pms_ocr_regula-14.0.1.0.2.dev3.dist-info/RECORD
